{
  "$schema": "https://developer.microsoft.com/json-schemas/fabric/item/report/definition/visualContainer/1.7.0/schema.json",
  "name": "1b64d764622e1130a81e",
  "position": {
    "x": 22.677165354330707,
    "y": 450.70866141732279,
    "z": 6000,
    "height": 259.37007874015745,
    "width": 549.9212598425197,
    "tabOrder": 3000
  },
  "visual": {
    "visualType": "map",
    "query": {
      "queryState": {
        "Category": {
          "projections": [
            {
              "field": {
                "Column": {
                  "Expression": {
                    "SourceRef": {
                      "Entity": "T_City"
                    }
                  },
                  "Property": "Country"
                }
              },
              "queryRef": "T_City.Country",
              "nativeQueryRef": "Country",
              "active": true
            },
            {
              "field": {
                "Column": {
                  "Expression": {
                    "SourceRef": {
                      "Entity": "T_City"
                    }
                  },
                  "Property": "State_Province"
                }
              },
              "queryRef": "T_City.State_Province",
              "nativeQueryRef": "State_Province",
              "active": true
            },
            {
              "field": {
                "Column": {
                  "Expression": {
                    "SourceRef": {
                      "Entity": "T_City"
                    }
                  },
                  "Property": "Region"
                }
              },
              "queryRef": "T_City.Region",
              "nativeQueryRef": "Region",
              "active": false
            }
          ]
        },
        "Size": {
          "projections": [
            {
              "field": {
                "Aggregation": {
                  "Expression": {
                    "Column": {
                      "Expression": {
                        "SourceRef": {
                          "Entity": "T_Sales"
                        }
                      },
                      "Property": "DeliveryTimeDays"
                    }
                  },
                  "Function": 1
                }
              },
              "queryRef": "Sum(T_Sales.DeliveryTimeDays)",
              "nativeQueryRef": "Promedio de DeliveryTimeDays"
            }
          ]
        }
      }
    },
    "objects": {
      "heatMap": [
        {
          "properties": {
            "show": {
              "expr": {
                "Literal": {
                  "Value": "false"
                }
              }
            },
            "color50": {
              "solid": {
                "color": {
                  "expr": {
                    "ThemeDataColor": {
                      "ColorId": 8,
                      "Percent": 0
                    }
                  }
                }
              }
            },
            "color0": {
              "solid": {
                "color": {
                  "expr": {
                    "Literal": {
                      "Value": "'#0FFF0F'"
                    }
                  }
                }
              }
            },
            "color100": {
              "solid": {
                "color": {
                  "expr": {
                    "ThemeDataColor": {
                      "ColorId": 9,
                      "Percent": -0.25
                    }
                  }
                }
              }
            }
          }
        }
      ],
      "dataPoint": [
        {
          "properties": {
            "showAllDataPoints": {
              "expr": {
                "Literal": {
                  "Value": "false"
                }
              }
            }
          }
        },
        {
          "properties": {
            "fill": {
              "solid": {
                "color": {
                  "expr": {
                    "Measure": {
                      "Expression": {
                        "SourceRef": {
                          "Entity": "Measure"
                        }
                      },
                      "Property": "DeliveryTimeColor"
                    }
                  }
                }
              }
            }
          },
          "selector": {
            "data": [
              {
                "dataViewWildcard": {
                  "matchingOption": 1
                }
              }
            ]
          }
        }
      ]
    },
    "visualContainerObjects": {
      "title": [
        {
          "properties": {
            "text": {
              "expr": {
                "Literal": {
                  "Value": "'Delivery Time Alerts'"
                }
              }
            },
            "fontColor": {
              "solid": {
                "color": {
                  "expr": {
                    "Literal": {
                      "Value": "'#F2F7FB'"
                    }
                  }
                }
              }
            },
            "background": {
              "solid": {
                "color": {
                  "expr": {
                    "Literal": {
                      "Value": "'#114E75'"
                    }
                  }
                }
              }
            },
            "alignment": {
              "expr": {
                "Literal": {
                  "Value": "'center'"
                }
              }
            }
          }
        }
      ]
    },
    "drillFilterOtherVisuals": true
  }
}